round_robin_tournament/__init__.py
round_robin_tournament/match.py
round_robin_tournament/participant.py
round_robin_tournament/tournament.py
round_robin_tournament-1.0.0.dist-info/LICENSE
round_robin_tournament-1.0.0.dist-info/METADATA
round_robin_tournament-1.0.0.dist-info/WHEEL
round_robin_tournament-1.0.0.dist-info/top_level.txt
round_robin_tournament-1.0.0.dist-info/RECORD
