Metadata-Version: 2.1
Name: round-robin-tournament
Version: 1.0.0
Summary: A round robin tournament match handler.
Home-page: https://github.com/smwa/round_robin_tournament
Author: Michael Smith
Author-email: michael.smith.ok@gmail.com
License: UNKNOWN
Platform: UNKNOWN
Classifier: Programming Language :: Python :: 3
Classifier: License :: OSI Approved :: MIT License
Classifier: Operating System :: OS Independent
Requires-Python: >=3.6
